<?xml version = '1.0' encoding = 'UTF-8'?>
<Diagram class="oracle.dbtools.crest.swingui.datatypes.DPVDataTypes" id="0C093A67-7E88-185C-A608-7E745FFBF8EA">
<createdBy>beto</createdBy>
<modifiedBy>beto</modifiedBy>
<createdTime>2023-05-22 16:26:21 UTC</createdTime>
<autoRoute>false</autoRoute>
<boxInbox>true</boxInbox>
<showLegend>false</showLegend>
<showLabels>true</showLabels>
<showRelAttributes>false</showRelAttributes>
<gridEnabled>false</gridEnabled>
<showGrid>false</showGrid>
<diagramColor>-1</diagramColor>
<display>false</display>
<notation>1</notation>
<objectViews>
<OView class="oracle.dbtools.crest.swingui.datatypes.TVStructuredType" oid="47E390DE-0671-C4B1-8428-0F45CBEE18F8" otype="StructuredType" vid="362682A3-5509-F9FB-2285-BC82A9C803F7">
<hideElementsInCurrentOnly>false</hideElementsInCurrentOnly>
<bounds x="20" y="20" width="108" height="39"/>
</OView>
<OView class="oracle.dbtools.crest.swingui.datatypes.TVStructuredType" oid="F72C39E0-D1CA-8821-2AD7-A1E95A37D3D1" otype="StructuredType" vid="F7C24383-4386-B6A1-81AC-5BD569E991DE">
<hideElementsInCurrentOnly>false</hideElementsInCurrentOnly>
<bounds x="178" y="20" width="78" height="39"/>
</OView>
</objectViews>
</Diagram>